{
  "main": {
    "id": "f56708867f7d6eb4",
    "type": "split",
    "children": [
      {
        "id": "66355bd0bd9bc2f1",
        "type": "tabs",
        "children": [
          {
            "id": "c64e7d5c9d38facc",
            "type": "leaf",
            "state": {
              "type": "markdown",
              "state": {
                "file": "src/area/other/拿到一台新 Mac 后，我需要做些什么？.md",
                "mode": "source",
                "source": false,
                "backlinks": false
              },
              "icon": "lucide-file",
              "title": "拿到一台新 Mac 后，我需要做些什么？"
            }
          },
          {
            "id": "d197660a6bc82547",
            "type": "leaf",
            "state": {
              "type": "split-diff-view",
              "state": {
                "aFile": "src/area/tech/README.md",
                "bFile": "src/area/tech/README.md",
                "aRef": ""
              },
              "icon": "diff",
              "title": "Diff: README"
            }
          },
          {
            "id": "009d7cda45ec3bda",
            "type": "leaf",
            "state": {
              "type": "split-diff-view",
              "state": {
                "aFile": "src/inbox/为什么互联网公司都在逐步弃用 Cookie？.md",
                "bFile": "src/inbox/为什么互联网公司都在逐步弃用 Cookie？.md",
                "aRef": ""
              },
              "icon": "diff",
              "title": "Diff: 为什么互联网公司都在逐步弃用 Cookie？"
            }
          },
          {
            "id": "f073daf39baa3aff",
            "type": "leaf",
            "state": {
              "type": "markdown",
              "state": {
                "file": "src/inbox/为什么要做对账和幂等？.md",
                "mode": "source",
                "source": false,
                "backlinks": false
              },
              "icon": "lucide-file",
              "title": "为什么要做对账和幂等？"
            }
          },
          {
            "id": "84b60f10c10a51c1",
            "type": "leaf",
            "state": {
              "type": "markdown",
              "state": {
                "file": "src/project/Interview/场景题/接口优化技巧.md",
                "mode": "source",
                "source": false,
                "backlinks": false
              },
              "icon": "lucide-file",
              "title": "接口优化技巧"
            }
          },
          {
            "id": "1391e329ef82aaaf",
            "type": "leaf",
            "state": {
              "type": "markdown",
              "state": {
                "file": "src/area/log_for_life/weekly/第 12 期：SakuraSakura.md",
                "mode": "source",
                "source": false,
                "backlinks": false
              },
              "icon": "lucide-file",
              "title": "第 12 期：SakuraSakura"
            }
          },
          {
            "id": "f4def11747275b35",
            "type": "leaf",
            "state": {
              "type": "markdown",
              "state": {
                "file": "src/area/lifestyle/README.md",
                "mode": "source",
                "source": false,
                "backlinks": false
              },
              "icon": "lucide-file",
              "title": "README"
            }
          },
          {
            "id": "92167dc7f66403f2",
            "type": "leaf",
            "state": {
              "type": "markdown",
              "state": {
                "file": "src/area/tech/React Native/React Native 中通过蓝牙连接汉印标签打印机 D35BT.md",
                "mode": "source",
                "source": false,
                "backlinks": false
              },
              "icon": "lucide-file",
              "title": "React Native 中通过蓝牙连接汉印标签打印机 D35BT"
            }
          },
          {
            "id": "12b28afd792be2ae",
            "type": "leaf",
            "state": {
              "type": "markdown",
              "state": {
                "file": "src/area/other/life_guidelines.md",
                "mode": "source",
                "source": false,
                "backlinks": false
              },
              "icon": "lucide-file",
              "title": "life_guidelines"
            }
          },
          {
            "id": "9a02910e0ba566bc",
            "type": "leaf",
            "state": {
              "type": "split-diff-view",
              "state": {
                "aFile": "src/area/other/website_navigation.md",
                "bFile": "src/area/other/website_navigation.md",
                "aRef": ""
              },
              "icon": "diff",
              "title": "Diff: website_navigation"
            }
          },
          {
            "id": "ff7e7f1729c653a2",
            "type": "leaf",
            "state": {
              "type": "markdown",
              "state": {
                "file": "src/area/other/website_navigation.md",
                "mode": "source",
                "source": false,
                "backlinks": false
              },
              "icon": "lucide-file",
              "title": "website_navigation"
            }
          }
        ]
      }
    ],
    "direction": "vertical"
  },
  "left": {
    "id": "f0aa35c024c17b15",
    "type": "split",
    "children": [
      {
        "id": "c65be39da4b31782",
        "type": "tabs",
        "children": [
          {
            "id": "49813a896445e999",
            "type": "leaf",
            "state": {
              "type": "file-explorer",
              "state": {
                "sortOrder": "alphabetical",
                "autoReveal": false
              },
              "icon": "lucide-folder-closed",
              "title": "文件列表"
            }
          },
          {
            "id": "8337d5b489e0c543",
            "type": "leaf",
            "state": {
              "type": "search",
              "state": {
                "query": "tag:Expo",
                "matchingCase": false,
                "explainSearch": false,
                "collapseAll": false,
                "extraContext": false,
                "sortOrder": "alphabetical"
              },
              "icon": "lucide-search",
              "title": "Search"
            }
          },
          {
            "id": "e4a27fda7aaef96b",
            "type": "leaf",
            "state": {
              "type": "recent-files",
              "state": {},
              "icon": "lucide-file",
              "title": "插件不再活动"
            }
          }
        ]
      }
    ],
    "direction": "horizontal",
    "width": 365.5
  },
  "right": {
    "id": "6e149d68010dd5c0",
    "type": "split",
    "children": [
      {
        "id": "d2b26903d4ccb216",
        "type": "tabs",
        "children": [
          {
            "id": "3a67fe72c8cb4b00",
            "type": "leaf",
            "state": {
              "type": "tag",
              "state": {
                "sortOrder": "frequency",
                "useHierarchy": false,
                "showSearch": false,
                "searchQuery": ""
              },
              "icon": "lucide-tags",
              "title": "Tags"
            }
          },
          {
            "id": "ac33791abec12b73",
            "type": "leaf",
            "state": {
              "type": "git-view",
              "state": {},
              "icon": "git-pull-request",
              "title": "Source Control"
            }
          },
          {
            "id": "0ffe64b7ef3a3a9c",
            "type": "leaf",
            "state": {
              "type": "outgoing-link",
              "state": {
                "file": "src/area/other/website_navigation.md",
                "linksCollapsed": false,
                "unlinkedCollapsed": true
              },
              "icon": "links-going-out",
              "title": "Outgoing links from website_navigation"
            }
          },
          {
            "id": "007323d7114f7cb1",
            "type": "leaf",
            "state": {
              "type": "all-properties",
              "state": {
                "sortOrder": "frequency",
                "showSearch": false,
                "searchQuery": ""
              },
              "icon": "lucide-archive",
              "title": "All properties"
            }
          },
          {
            "id": "2b4c55771cb2c52f",
            "type": "leaf",
            "state": {
              "type": "file-properties",
              "state": {
                "file": "src/area/other/website_navigation.md"
              },
              "icon": "lucide-info",
              "title": "File properties for website_navigation"
            }
          },
          {
            "id": "dac3d694e359bb69",
            "type": "leaf",
            "state": {
              "type": "advanced-tables-toolbar",
              "state": {},
              "icon": "spreadsheet",
              "title": "Advanced Tables"
            }
          },
          {
            "id": "6ed19ffb7b517218",
            "type": "leaf",
            "state": {
              "type": "outline",
              "state": {
                "file": "src/area/other/website_navigation.md",
                "followCursor": false,
                "showSearch": false,
                "searchQuery": ""
              },
              "icon": "lucide-list",
              "title": "Outline of website_navigation"
            }
          }
        ],
        "currentTab": 1
      }
    ],
    "direction": "horizontal",
    "width": 324.5
  },
  "left-ribbon": {
    "hiddenItems": {
      "switcher:打开快速切换": false,
      "graph:查看关系图谱": false,
      "templates:插入模板": false,
      "obsidian-git:Open Git source control": false,
      "excalidraw-cn:Create New Excalidraw File": false,
      "omnisearch:Omnisearch": false,
      "table-editor-obsidian:Advanced Tables Toolbar": false
    }
  },
  "active": "c64e7d5c9d38facc",
  "lastOpenFiles": [
    "src/area/other/website_navigation.md",
    "src/inbox/为什么要做对账和幂等？.md",
    "src/area/other/life_guidelines.md",
    "src/area/tech/React Native/React Native 中通过蓝牙连接汉印标签打印机 D35BT.md",
    "src/area/tech/React Native/README.md",
    "src/area/tech/README.md",
    "src/area/other/拿到一台新 Mac 后，我需要做些什么？.md",
    "src/area/log_for_life/weekly/第 12 期：SakuraSakura.md",
    "src/area/log_for_life/weekly/第 1 期：换了新手机.md",
    "src/project/Interview/场景题/接口优化技巧.md",
    "src/area/lifestyle/README.md",
    "src/area/other/README.md",
    "src/area/tech/React Native",
    "Untitled.md",
    "src/area/log_for_life/weekly/第 9 期：人生 SOP.md",
    "src/area/log_for_life/weekly/第 11 期：追逐落日.md",
    "src/area/log_for_life/weekly/第 10 期：时间管理.md",
    "src/area/log_for_life/weekly/第 7 期：南京博物院.md",
    "the_draft/draft.md",
    "src/inbox/Redis 的大 Key 问题.md",
    "src/inbox/为什么互联网公司都在逐步弃用 Cookie？.md",
    "the_draft/white_board.ex",
    "src/inbox/未命名 2.md",
    "src/area/log_for_life/weekly/第 8 期：转职木工.md",
    "src/project/未命名.md",
    "src/resource/并发常见问题.md",
    "src/resource/分布式锁可以解决什么问题？.md",
    "src/resource/为什么消息至少投递成功一次，但没有办法保证只投递一次？.md",
    "src/area/lifestyle/家装改造计划/draft/white_board.ex",
    "src/area/lifestyle/家装改造计划/draft",
    "src/area/lifestyle/家装改造计划",
    "src/area/log_for_life/travel",
    "src/area/log_for_life/plan",
    "src/area/log_for_life",
    "src/area/log_for_life/weekly",
    "src/01_Log/周刊",
    "未命名.canvas",
    "src/01_daliy/05_终身学习体系/230202_个人信息流分享.canvas",
    "node_modules/vuepress-theme-hope/lib/bundle/modules/blog/assets/hero.jpg",
    "node_modules/vuepress-theme-hope/templates/socialMediaIcons/telegram.svg",
    "node_modules/vuepress-theme-hope/templates/socialMediaIcons/skype.svg",
    "node_modules/vuepress-theme-hope/templates/socialMediaIcons/douban.svg",
    "node_modules/pngjs/coverage/lcov-report/sort-arrow-sprite.png",
    "node_modules/pngjs/coverage/lcov-report/favicon.png",
    "未命名 1.canvas",
    "node_modules/Pasted Image 20230619020653_991.png",
    "node_modules/Pasted Image 20230619020538_851.png",
    "node_modules/Pasted Image 20230619013827_803.png",
    "node_modules/Pasted Image 20230618173545_135.png",
    "src/02_program/00_todo/RocketMQ 刷盘机制流程图.canvas"
  ]
}